{
  "status": "success",
  "result": [
    {
      "id": 1,
      "type": "guest",
      "rating": 4,
      "publicReview": "Great stay, very clean and comfortable!",
      "reviewCategory": [
        { "category": "cleanliness", "rating": 5 },
        { "category": "communication", "rating": 4 },
        { "category": "respect_house_rules", "rating": 5 }
      ],
      "guestName": "Alice",
      "listingName": "Modern Flat",
      "submittedAt": "2023-11-01T12:00:00Z"
    },
    {
      "id": 2,
      "type": "guest",
      "rating": 3,
      "publicReview": "Good location, but noisy neighbors.",
      "reviewCategory": [
        { "category": "cleanliness", "rating": 3 },
        { "category": "communication", "rating": 4 },
        { "category": "respect_house_rules", "rating": 3 }
      ],
      "guestName": "Bob",
      "listingName": "City Apartment",
      "submittedAt": "2023-11-03T14:30:00Z"
    },
    {
      "id": 3,
      "type": "guest",
      "rating": 5,
      "publicReview": "Fantastic host and cozy place.",
      "reviewCategory": [
        { "category": "cleanliness", "rating": 5 },
        { "category": "communication", "rating": 5 },
        { "category": "respect_house_rules", "rating": 5 }
      ],
      "guestName": "Clara",
      "listingName": "Cozy Cottage",
      "submittedAt": "2023-11-05T10:00:00Z"
    },
    {
      "id": 4,
      "type": "guest",
      "rating": 2,
      "publicReview": "Dirty bathroom and poor communication.",
      "reviewCategory": [
        { "category": "cleanliness", "rating": 1 },
        { "category": "communication", "rating": 2 },
        { "category": "respect_house_rules", "rating": 2 }
      ],
      "guestName": "David",
      "listingName": "Budget Room",
      "submittedAt": "2023-11-06T18:45:00Z"
    },
    {
      "id": 5,
      "type": "guest",
      "rating": 5,
      "publicReview": "Wonderful experience, will come back again!",
      "reviewCategory": [
        { "category": "cleanliness", "rating": 5 },
        { "category": "communication", "rating": 5 },
        { "category": "respect_house_rules", "rating": 5 }
      ],
      "guestName": "Ella",
      "listingName": "Luxury Suite",
      "submittedAt": "2023-11-08T11:20:00Z"
    },
    {
      "id": 6,
      "type": "guest",
      "rating": 3,
      "publicReview": "Decent value for money.",
      "reviewCategory": [
        { "category": "cleanliness", "rating": 3 },
        { "category": "communication", "rating": 3 },
        { "category": "respect_house_rules", "rating": 3 }
      ],
      "guestName": "Frank",
      "listingName": "Studio Apartment",
      "submittedAt": "2023-11-10T09:10:00Z"
    },
    {
      "id": 7,
      "type": "guest",
      "rating": 4,
      "publicReview": "Nice view and comfy bed.",
      "reviewCategory": [
        { "category": "cleanliness", "rating": 4 },
        { "category": "communication", "rating": 4 },
        { "category": "respect_house_rules", "rating": 4 }
      ],
      "guestName": "Grace",
      "listingName": "Seaside House",
      "submittedAt": "2023-11-12T16:30:00Z"
    },
    {
      "id": 8,
      "type": "guest",
      "rating": 1,
      "publicReview": "Terrible experience, not recommended.",
      "reviewCategory": [
        { "category": "cleanliness", "rating": 1 },
        { "category": "communication", "rating": 1 },
        { "category": "respect_house_rules", "rating": 1 }
      ],
      "guestName": "Hank",
      "listingName": "Shared Room",
      "submittedAt": "2023-11-14T13:55:00Z"
    },
    {
      "id": 9,
      "type": "guest",
      "rating": 4,
      "publicReview": "Quiet neighborhood and good amenities.",
      "reviewCategory": [
        { "category": "cleanliness", "rating": 4 },
        { "category": "communication", "rating": 4 },
        { "category": "respect_house_rules", "rating": 5 }
      ],
      "guestName": "Irene",
      "listingName": "Suburban House",
      "submittedAt": "2023-11-16T07:45:00Z"
    },
    {
      "id": 10,
      "type": "guest",
      "rating": 5,
      "publicReview": "Exceptional service and beautiful place.",
      "reviewCategory": [
        { "category": "cleanliness", "rating": 5 },
        { "category": "communication", "rating": 5 },
        { "category": "respect_house_rules", "rating": 5 }
      ],
      "guestName": "Jake",
      "listingName": "Mountain Cabin",
      "submittedAt": "2023-11-18T15:00:00Z"
    },
    {
      "id": 11,
      "type": "guest",
      "rating": 3,
      "publicReview": "Good stay",
      "reviewCategory": [
        { "category": "cleanliness", "rating": 2 },
        { "category": "communication", "rating": 3 },
        { "category": "respect_house_rules", "rating": 4 }
      ],
      "guestName": "Malice",
      "listingName": "Western Flat",
      "submittedAt": "2023-11-01T12:00:00Z"
    },
    {
      "id": 12,
      "type": "guest",
      "rating": 4,
      "publicReview": "Nice location.",
      "reviewCategory": [
        { "category": "cleanliness", "rating": 4 },
        { "category": "communication", "rating": 4 },
        { "category": "respect_house_rules", "rating": 4 }
      ],
      "guestName": "Bob Miller",
      "listingName": "Town Apartment",
      "submittedAt": "2023-11-03T14:30:00Z"
    },
    {
      "id": 13,
      "type": "guest",
      "rating": 5,
      "publicReview": "Fantastic place.",
      "reviewCategory": [
        { "category": "cleanliness", "rating": 5 },
        { "category": "communication", "rating": 5 },
        { "category": "respect_house_rules", "rating": 5 }
      ],
      "guestName": "Chloe",
      "listingName": "Cool Cottage",
      "submittedAt": "2023-11-05T10:00:00Z"
    },
    {
      "id": 14,
      "type": "guest",
      "rating": 2,
      "publicReview": "Excellent.",
      "reviewCategory": [
        { "category": "cleanliness", "rating": 5 },
        { "category": "communication", "rating": 5 },
        { "category": "respect_house_rules", "rating": 5 }
      ],
      "guestName": "Boon",
      "listingName": "Budget Friendly Room",
      "submittedAt": "2023-11-06T18:45:00Z"
    },
    {
      "id": 15,
      "type": "guest",
      "rating": 1,
      "publicReview": "Worst experience",
      "reviewCategory": [
        { "category": "cleanliness", "rating": 1 },
        { "category": "communication", "rating": 1 },
        { "category": "respect_house_rules", "rating": 1 }
      ],
      "guestName": "Bella",
      "listingName": "Cheap Suite",
      "submittedAt": "2023-11-08T11:20:00Z"
    },
    {
      "id": 16,
      "type": "guest",
      "rating": 3,
      "publicReview": "Value for money.",
      "reviewCategory": [
        { "category": "cleanliness", "rating": 3 },
        { "category": "communication", "rating": 3 },
        { "category": "respect_house_rules", "rating": 3 }
      ],
      "guestName": "Chapra",
      "listingName": "Studio",
      "submittedAt": "2023-11-10T09:10:00Z"
    },
    {
      "id": 17,
      "type": "guest",
      "rating": 2,
      "publicReview": "Nice view but poor maintenance.",
      "reviewCategory": [
        { "category": "cleanliness", "rating": 1 },
        { "category": "communication", "rating": 3 },
        { "category": "respect_house_rules", "rating": 2 }
      ],
      "guestName": "Disgrace",
      "listingName": "Beachside Mouse",
      "submittedAt": "2023-11-12T16:30:00Z"
    },
    {
      "id": 18,
      "type": "guest",
      "rating": 1,
      "publicReview": "Terrible experience, not recommended.",
      "reviewCategory": [
        { "category": "cleanliness", "rating": 1 },
        { "category": "communication", "rating": 1 },
        { "category": "respect_house_rules", "rating": 1 }
      ],
      "guestName": "Tom",
      "listingName": "Shared Room",
      "submittedAt": "2023-11-14T13:55:00Z"
    },
    {
      "id": 19,
      "type": "guest",
      "rating": 4,
      "publicReview": "Quiet neighborhood and good amenities.",
      "reviewCategory": [
        { "category": "cleanliness", "rating": 4 },
        { "category": "communication", "rating": 4 },
        { "category": "respect_house_rules", "rating": 4 }
      ],
      "guestName": "Dunnes",
      "listingName": "Rural House",
      "submittedAt": "2023-11-16T07:45:00Z"
    },
    {
      "id": 20,
      "type": "guest",
      "rating": 5,
      "publicReview": "Exceptional service and beautiful place.",
      "reviewCategory": [
        { "category": "cleanliness", "rating": 5 },
        { "category": "communication", "rating": 5 },
        { "category": "respect_house_rules", "rating": 5 }
      ],
      "guestName": "Jacob",
      "listingName": "Fountain Cabin",
      "submittedAt": "2023-11-18T15:00:00Z"
    },
    {
      "id": 21,
      "type": "guest",
      "status": "published",
      "rating": 3.5,
      "publicReview": "Lorem ipsum dolor sit amet, consectetur adipiscing elit.",
      "reviewCategory": [
        {
          "category": "cleanliness",
          "rating": 5.0
        },
        {
          "category": "communication",
          "rating": 3.5
        },
        {
          "category": "respect_house_rules",
          "rating": 4.0
        }
      ],
      "guestName": "Hannah",
      "listingName": "Soho Loft",
      "submittedAt": "2025-08-16T00:00:00"
    },
    {
      "id": 22,
      "type": "host",
      "status": "published",
      "rating": 3.5,
      "publicReview": "Lorem ipsum dolor sit amet, consectetur adipiscing elit.",
      "reviewCategory": [
        {
          "category": "cleanliness",
          "rating": 4.5
        },
        {
          "category": "communication",
          "rating": 4.0
        },
        {
          "category": "respect_house_rules",
          "rating": 4.0
        }
      ],
      "guestName": "Fiona",
      "listingName": "Soho Loft",
      "submittedAt": "2025-08-16T00:00:00"
    },
    {
      "id": 23,
      "type": "host",
      "status": "published",
      "rating": 4.5,
      "publicReview": "Lorem ipsum dolor sit amet, consectetur adipiscing elit.",
      "reviewCategory": [
        {
          "category": "cleanliness",
          "rating": 5.0
        },
        {
          "category": "communication",
          "rating": 4.5
        },
        {
          "category": "respect_house_rules",
          "rating": 4.5
        }
      ],
      "guestName": "George",
      "listingName": "London Bridge Apt",
      "submittedAt": "2025-08-16T00:00:00"
    },
    {
      "id": 24,
      "type": "host",
      "status": "published",
      "rating": 4.0,
      "publicReview": "Lorem ipsum dolor sit amet, consectetur adipiscing elit.",
      "reviewCategory": [
        {
          "category": "cleanliness",
          "rating": 4.5
        },
        {
          "category": "communication",
          "rating": 4.0
        },
        {
          "category": "respect_house_rules",
          "rating": 3.5
        }
      ],
      "guestName": "Ian",
      "listingName": "London Bridge Apt",
      "submittedAt": "2025-08-16T00:00:00"
    },
    {
      "id": 25,
      "type": "guest",
      "status": "published",
      "rating": 4.5,
      "publicReview": "Lorem ipsum dolor sit amet, consectetur adipiscing elit.",
      "reviewCategory": [
        {
          "category": "cleanliness",
          "rating": 4.0
        },
        {
          "category": "communication",
          "rating": 4.0
        },
        {
          "category": "respect_house_rules",
          "rating": 4.5
        }
      ],
      "guestName": "Diana",
      "listingName": "Soho Loft",
      "submittedAt": "2025-08-16T00:00:00"
    },
    {
      "id": 26,
      "type": "host",
      "status": "published",
      "rating": 4.5,
      "publicReview": "Lorem ipsum dolor sit amet, consectetur adipiscing elit.",
      "reviewCategory": [
        {
          "category": "cleanliness",
          "rating": 4.5
        },
        {
          "category": "communication",
          "rating": 4.5
        },
        {
          "category": "respect_house_rules",
          "rating": 4.5
        }
      ],
      "guestName": "George",
      "listingName": "London Bridge Apt",
      "submittedAt": "2025-08-15T00:00:00"
    },
    {
      "id": 27,
      "type": "guest",
      "status": "published",
      "rating": 4.5,
      "publicReview": "Lorem ipsum dolor sit amet, consectetur adipiscing elit.",
      "reviewCategory": [
        {
          "category": "cleanliness",
          "rating": 3.5
        },
        {
          "category": "communication",
          "rating": 4.5
        },
        {
          "category": "respect_house_rules",
          "rating": 3.5
        }
      ],
      "guestName": "George",
      "listingName": "Soho Loft",
      "submittedAt": "2025-08-16T00:00:00"
    },
    {
      "id": 28,
      "type": "guest",
      "status": "published",
      "rating": 4.5,
      "publicReview": "Lorem ipsum dolor sit amet, consectetur adipiscing elit.",
      "reviewCategory": [
        {
          "category": "cleanliness",
          "rating": 4.5
        },
        {
          "category": "communication",
          "rating": 4.5
        },
        {
          "category": "respect_house_rules",
          "rating": 5.0
        }
      ],
      "guestName": "Bob",
      "listingName": "London Bridge Apt",
      "submittedAt": "2025-08-24T00:00:00"
    },
    {
      "id": 29,
      "type": "host",
      "status": "published",
      "rating": 4.0,
      "publicReview": "Lorem ipsum dolor sit amet, consectetur adipiscing elit.",
      "reviewCategory": [
        {
          "category": "cleanliness",
          "rating": 4.5
        },
        {
          "category": "communication",
          "rating": 5.0
        },
        {
          "category": "respect_house_rules",
          "rating": 4.5
        }
      ],
      "guestName": "George",
      "listingName": "Greenwich Home",
      "submittedAt": "2025-08-15T00:00:00"
    },
    {
      "id": 30,
      "type": "guest",
      "status": "published",
      "rating": 5.0,
      "publicReview": "Lorem ipsum dolor sit amet, consectetur adipiscing elit.",
      "reviewCategory": [
        {
          "category": "cleanliness",
          "rating": 5.0
        },
        {
          "category": "communication",
          "rating": 3.5
        },
        {
          "category": "respect_house_rules",
          "rating": 4.5
        }
      ],
      "guestName": "Alice",
      "listingName": "London Bridge Apt",
      "submittedAt": "2025-08-15T00:00:00"
    },
    {
      "id": 31,
      "type": "guest",
      "status": "published",
      "rating": 5.0,
      "publicReview": "Lorem ipsum dolor sit amet, consectetur adipiscing elit.",
      "reviewCategory": [
        {
          "category": "cleanliness",
          "rating": 3.5
        },
        {
          "category": "communication",
          "rating": 4.0
        },
        {
          "category": "respect_house_rules",
          "rating": 4.0
        }
      ],
      "guestName": "Hannah",
      "listingName": "London Bridge Apt",
      "submittedAt": "2025-08-16T00:00:00"
    },
    {
      "id": 32,
      "type": "host",
      "status": "published",
      "rating": 5.0,
      "publicReview": "Lorem ipsum dolor sit amet, consectetur adipiscing elit.",
      "reviewCategory": [
        {
          "category": "cleanliness",
          "rating": 4.5
        },
        {
          "category": "communication",
          "rating": 5.0
        },
        {
          "category": "respect_house_rules",
          "rating": 5.0
        }
      ],
      "guestName": "Bob",
      "listingName": "London Bridge Apt",
      "submittedAt": "2025-08-15T00:00:00"
    },
    {
      "id": 33,
      "type": "guest",
      "status": "published",
      "rating": 3.5,
      "publicReview": "Lorem ipsum dolor sit amet, consectetur adipiscing elit.",
      "reviewCategory": [
        {
          "category": "cleanliness",
          "rating": 4.0
        },
        {
          "category": "communication",
          "rating": 3.5
        },
        {
          "category": "respect_house_rules",
          "rating": 4.0
        }
      ],
      "guestName": "Fiona",
      "listingName": "London Bridge Apt",
      "submittedAt": "2025-08-16T00:00:00"
    },
    {
      "id": 34,
      "type": "host",
      "status": "published",
      "rating": 3.5,
      "publicReview": "Lorem ipsum dolor sit amet, consectetur adipiscing elit.",
      "reviewCategory": [
        {
          "category": "cleanliness",
          "rating": 4.0
        },
        {
          "category": "communication",
          "rating": 4.0
        },
        {
          "category": "respect_house_rules",
          "rating": 5.0
        }
      ],
      "guestName": "Julia",
      "listingName": "Camden Town Flat",
      "submittedAt": "2025-08-20T00:00:00"
    },
    {
      "id": 35,
      "type": "host",
      "status": "published",
      "rating": 5.0,
      "publicReview": "Lorem ipsum dolor sit amet, consectetur adipiscing elit.",
      "reviewCategory": [
        {
          "category": "cleanliness",
          "rating": 3.5
        },
        {
          "category": "communication",
          "rating": 4.5
        },
        {
          "category": "respect_house_rules",
          "rating": 4.0
        }
      ],
      "guestName": "Ian",
      "listingName": "Greenwich Home",
      "submittedAt": "2025-08-19T00:00:00"
    },
    {
      "id": 36,
      "type": "host",
      "status": "published",
      "rating": 4.0,
      "publicReview": "Lorem ipsum dolor sit amet, consectetur adipiscing elit.",
      "reviewCategory": [
        {
          "category": "cleanliness",
          "rating": 4.0
        },
        {
          "category": "communication",
          "rating": 3.5
        },
        {
          "category": "respect_house_rules",
          "rating": 4.5
        }
      ],
      "guestName": "Charlie",
      "listingName": "London Bridge Apt",
      "submittedAt": "2025-08-21T00:00:00"
    },
    {
      "id": 37,
      "type": "guest",
      "status": "published",
      "rating": 4.5,
      "publicReview": "Lorem ipsum dolor sit amet, consectetur adipiscing elit.",
      "reviewCategory": [
        {
          "category": "cleanliness",
          "rating": 5.0
        },
        {
          "category": "communication",
          "rating": 4.5
        },
        {
          "category": "respect_house_rules",
          "rating": 4.0
        }
      ],
      "guestName": "Alice",
      "listingName": "Camden Town Flat",
      "submittedAt": "2025-08-16T00:00:00"
    },
    {
      "id": 38,
      "type": "host",
      "status": "published",
      "rating": 3.5,
      "publicReview": "Lorem ipsum dolor sit amet, consectetur adipiscing elit.",
      "reviewCategory": [
        {
          "category": "cleanliness",
          "rating": 4.0
        },
        {
          "category": "communication",
          "rating": 3.5
        },
        {
          "category": "respect_house_rules",
          "rating": 4.5
        }
      ],
      "guestName": "Alice",
      "listingName": "Soho Loft",
      "submittedAt": "2025-08-25T00:00:00"
    },
    {
      "id": 39,
      "type": "guest",
      "status": "published",
      "rating": 3.5,
      "publicReview": "Lorem ipsum dolor sit amet, consectetur adipiscing elit.",
      "reviewCategory": [
        {
          "category": "cleanliness",
          "rating": 4.5
        },
        {
          "category": "communication",
          "rating": 5.0
        },
        {
          "category": "respect_house_rules",
          "rating": 3.5
        }
      ],
      "guestName": "Fiona",
      "listingName": "London Bridge Apt",
      "submittedAt": "2025-08-17T00:00:00"
    },
    {
      "id": 40,
      "type": "host",
      "status": "published",
      "rating": 4.0,
      "publicReview": "Lorem ipsum dolor sit amet, consectetur adipiscing elit.",
      "reviewCategory": [
        {
          "category": "cleanliness",
          "rating": 4.0
        },
        {
          "category": "communication",
          "rating": 5.0
        },
        {
          "category": "respect_house_rules",
          "rating": 3.5
        }
      ],
      "guestName": "Bob",
      "listingName": "London Bridge Apt",
      "submittedAt": "2025-08-15T00:00:00"
    },
    {
      "id": 41,
      "type": "host",
      "status": "published",
      "rating": 5.0,
      "publicReview": "Lorem ipsum dolor sit amet, consectetur adipiscing elit.",
      "reviewCategory": [
        {
          "category": "cleanliness",
          "rating": 4.0
        },
        {
          "category": "communication",
          "rating": 5.0
        },
        {
          "category": "respect_house_rules",
          "rating": 3.5
        }
      ],
      "guestName": "Diana",
      "listingName": "Camden Town Flat",
      "submittedAt": "2025-08-15T00:00:00"
    },
    {
      "id": 42,
      "type": "guest",
      "status": "published",
      "rating": 3.5,
      "publicReview": "Lorem ipsum dolor sit amet, consectetur adipiscing elit.",
      "reviewCategory": [
        {
          "category": "cleanliness",
          "rating": 5.0
        },
        {
          "category": "communication",
          "rating": 4.5
        },
        {
          "category": "respect_house_rules",
          "rating": 4.0
        }
      ],
      "guestName": "Julia",
      "listingName": "Camden Town Flat",
      "submittedAt": "2025-08-15T00:00:00"
    },
    {
      "id": 43,
      "type": "guest",
      "status": "published",
      "rating": 3.5,
      "publicReview": "Lorem ipsum dolor sit amet, consectetur adipiscing elit.",
      "reviewCategory": [
        {
          "category": "cleanliness",
          "rating": 3.5
        },
        {
          "category": "communication",
          "rating": 5.0
        },
        {
          "category": "respect_house_rules",
          "rating": 4.0
        }
      ],
      "guestName": "Julia",
      "listingName": "Camden Town Flat",
      "submittedAt": "2025-08-15T00:00:00"
    },
    {
      "id": 44,
      "type": "guest",
      "status": "published",
      "rating": 4.5,
      "publicReview": "Lorem ipsum dolor sit amet, consectetur adipiscing elit.",
      "reviewCategory": [
        {
          "category": "cleanliness",
          "rating": 4.0
        },
        {
          "category": "communication",
          "rating": 3.5
        },
        {
          "category": "respect_house_rules",
          "rating": 5.0
        }
      ],
      "guestName": "Fiona",
      "listingName": "London Bridge Apt",
      "submittedAt": "2025-08-16T00:00:00"
    },
    {
      "id": 45,
      "type": "host",
      "status": "published",
      "rating": 5.0,
      "publicReview": "Lorem ipsum dolor sit amet, consectetur adipiscing elit.",
      "reviewCategory": [
        {
          "category": "cleanliness",
          "rating": 5.0
        },
        {
          "category": "communication",
          "rating": 5.0
        },
        {
          "category": "respect_house_rules",
          "rating": 4.0
        }
      ],
      "guestName": "Charlie",
      "listingName": "Soho Loft",
      "submittedAt": "2025-08-15T00:00:00"
    },
    {
      "id": 46,
      "type": "host",
      "status": "published",
      "rating": 4.0,
      "publicReview": "Lorem ipsum dolor sit amet, consectetur adipiscing elit.",
      "reviewCategory": [
        {
          "category": "cleanliness",
          "rating": 5.0
        },
        {
          "category": "communication",
          "rating": 4.5
        },
        {
          "category": "respect_house_rules",
          "rating": 3.5
        }
      ],
      "guestName": "Julia",
      "listingName": "London Bridge Apt",
      "submittedAt": "2025-08-16T00:00:00"
    },
    {
      "id": 47,
      "type": "host",
      "status": "published",
      "rating": 5.0,
      "publicReview": "Lorem ipsum dolor sit amet, consectetur adipiscing elit.",
      "reviewCategory": [
        {
          "category": "cleanliness",
          "rating": 4.5
        },
        {
          "category": "communication",
          "rating": 4.0
        },
        {
          "category": "respect_house_rules",
          "rating": 3.5
        }
      ],
      "guestName": "Fiona",
      "listingName": "Camden Town Flat",
      "submittedAt": "2025-08-23T00:00:00"
    },
    {
      "id": 48,
      "type": "guest",
      "status": "published",
      "rating": 3.5,
      "publicReview": "Lorem ipsum dolor sit amet, consectetur adipiscing elit.",
      "reviewCategory": [
        {
          "category": "cleanliness",
          "rating": 4.0
        },
        {
          "category": "communication",
          "rating": 4.5
        },
        {
          "category": "respect_house_rules",
          "rating": 4.5
        }
      ],
      "guestName": "Ian",
      "listingName": "Camden Town Flat",
      "submittedAt": "2025-08-17T00:00:00"
    },
    {
      "id": 49,
      "type": "host",
      "status": "published",
      "rating": 3.5,
      "publicReview": "Lorem ipsum dolor sit amet, consectetur adipiscing elit.",
      "reviewCategory": [
        {
          "category": "cleanliness",
          "rating": 5.0
        },
        {
          "category": "communication",
          "rating": 5.0
        },
        {
          "category": "respect_house_rules",
          "rating": 4.5
        }
      ],
      "guestName": "Charlie",
      "listingName": "London Bridge Apt",
      "submittedAt": "2025-08-16T00:00:00"
    },
    {
      "id": 50,
      "type": "host",
      "status": "published",
      "rating": 4.5,
      "publicReview": "Lorem ipsum dolor sit amet, consectetur adipiscing elit.",
      "reviewCategory": [
        {
          "category": "cleanliness",
          "rating": 3.5
        },
        {
          "category": "communication",
          "rating": 4.0
        },
        {
          "category": "respect_house_rules",
          "rating": 4.5
        }
      ],
      "guestName": "George",
      "listingName": "Camden Town Flat",
      "submittedAt": "2025-08-15T00:00:00"
    }
  ]
}
